llm_api/__init__.py
llm_api/_base_client.py
llm_api/_client.py
llm_api/_compat.py
llm_api/_constants.py
llm_api/_exceptions.py
llm_api/_files.py
llm_api/_models.py
llm_api/_qs.py
llm_api/_resource.py
llm_api/_response.py
llm_api/_streaming.py
llm_api/_types.py
llm_api/_version.py
llm_api/py.typed
llm_api/_utils/__init__.py
llm_api/_utils/_compat.py
llm_api/_utils/_datetime_parse.py
llm_api/_utils/_logs.py
llm_api/_utils/_proxy.py
llm_api/_utils/_reflection.py
llm_api/_utils/_resources_proxy.py
llm_api/_utils/_streams.py
llm_api/_utils/_sync.py
llm_api/_utils/_transform.py
llm_api/_utils/_typing.py
llm_api/_utils/_utils.py
llm_api/lib/.keep
llm_api/resources/__init__.py
llm_api/resources/audio.py
llm_api/resources/batches.py
llm_api/resources/chat.py
llm_api/resources/files.py
llm_api/resources/images.py
llm_api/resources/models.py
llm_api/types/__init__.py
llm_api/types/audio_create_transcription_params.py
llm_api/types/batch_cancel_response.py
llm_api/types/batch_create_params.py
llm_api/types/batch_create_response.py
llm_api/types/batch_list_params.py
llm_api/types/chat_create_completion_params.py
llm_api/types/file_list_params.py
llm_api/types/file_upload_params.py
llm_api/types/image_generate_params.py
llm_api_multiple-1.0.5.dist-info/METADATA
llm_api_multiple-1.0.5.dist-info/WHEEL
llm_api_multiple-1.0.5.dist-info/licenses/LICENSE
llm_api_multiple-1.0.5.dist-info/RECORD
